yscope_clp_core/__init__.py
yscope_clp_core/_api.py
yscope_clp_core/_archive_io.py
yscope_clp_core/_bin.py
yscope_clp_core/_config.py
yscope_clp_core/_except.py
yscope_clp_core/_utils.py
yscope_clp_core/bin/clp-s
yscope_clp_core.libs/libbrotlicommon-6ce2a53c.so.1.0.6
yscope_clp_core.libs/libbrotlidec-811d1be3.so.1.0.6
yscope_clp_core.libs/libcom_err-730ca923.so.2.1
yscope_clp_core.libs/libcrypt-52aca757.so.1.1.0
yscope_clp_core.libs/libcrypto-bfee2032.so.1.1.1k
yscope_clp_core.libs/libcurl-14a7698c.so.4.5.0
yscope_clp_core.libs/libgssapi_krb5-323bbd21.so.2.2
yscope_clp_core.libs/libidn2-2f4a5893.so.0.3.6
yscope_clp_core.libs/libk5crypto-9a74ff38.so.3.1
yscope_clp_core.libs/libkeyutils-2777d33d.so.1.6
yscope_clp_core.libs/libkrb5-a55300e8.so.3.3
yscope_clp_core.libs/libkrb5support-e6594cfc.so.0.1
yscope_clp_core.libs/liblber-2-d20824ef.4.so.2.10.9
yscope_clp_core.libs/libldap-2-cea2a960.4.so.2.10.9
yscope_clp_core.libs/libnghttp2-39367a22.so.14.17.0
yscope_clp_core.libs/libpcre2-8-516f4c9d.so.0.7.1
yscope_clp_core.libs/libpsl-99becdd3.so.5.3.1
yscope_clp_core.libs/libsasl2-7de4d792.so.3.0.0
yscope_clp_core.libs/libselinux-d0805dcb.so.1
yscope_clp_core.libs/libssh-9f6d898c.so.4.8.7
yscope_clp_core.libs/libssl-658e53cd.so.1.1.1k
yscope_clp_core.libs/libunistring-05abdd40.so.2.1.0
yscope_clp_core.libs/libzstd-9d33c0d3.so.1.5.7
yscope_clp_core-0.7.1b2.dist-info/METADATA
yscope_clp_core-0.7.1b2.dist-info/WHEEL
yscope_clp_core-0.7.1b2.dist-info/entry_points.txt
yscope_clp_core-0.7.1b2.dist-info/RECORD
yscope_clp_core-0.7.1b2.dist-info/licenses/LICENSE
yscope_clp_core-0.7.1b2.dist-info/sboms/auditwheel.cdx.json
