Metadata-Version: 2.4
Name: yscope-clp-core
Version: 0.7.1b2
Summary: YScope CLP (Compressed Log Processor) Core Python Distribution
Author-Email: "YScope Inc." <dev@yscope.com>
License-Expression: Apache-2.0
Project-URL: Homepage, https://github.com/y-scope/clp
Project-URL: Issue Tracker, https://github.com/y-scope/clp/issues
Requires-Python: >=3.10
Requires-Dist: typing-extensions>=4.15.0
